{
  "info": {
    "_postman_id": "7f927cc1-b99b-43d9-a790-e41c4118f6f5",
    "name": "School Edu Sphere",
    "description": "Student API collection (Students, Parents, Academic Records).",
    "schema": "https://schema.getpostman.com/json/collection/v2.1.0/collection.json"
  },
  "item": [
    {
      "name": "Student",
      "item": [
        {
          "name": "Students",
          "item": [
            {
              "name": "Create Student",
              "request": {
                "method": "POST",
                "header": [
                  {
                    "key": "Content-Type",
                    "value": "application/json"
                  }
                ],
                "body": {
                  "mode": "raw",
                  "raw": "  {\n    \"schoolId\": \"6a474d2517e9c40cf971ccc8\",\n    \"admissionNo\": \"ADM-2026-003\",\n    \"studentId\": \"STD-003\",\n    \"rollNo\": \"8C-03\",\n    \"firstName\": \"Liam\",\n    \"lastName\": \"Williams\",\n    \"dob\": \"2014-08-22\",\n    \"gender\": \"MALE\",\n    \"bloodGroup\": \"O+\",\n    \"photoUrl\": \"https://images.unsplash.com/photo-1500648767791-00dcc994a43e\",\n    \"classId\": \"class-8c\",\n    \"sectionId\": \"section-c\",\n    \"hostelRoomId\": \"hostel-room-103\",\n    \"walletId\": \"wallet-std-003\",\n    \"parentId\": \"6a475192ae2722e4b9afefd2\",\n    \"medicalRecordId\": \"med-std-003\",\n    \"status\": \"ACTIVE\",\n    \"admissionDate\": \"2026-06-03\"\n  }"
                },
                "url": {
                  "raw": "http://localhost:5030/api/students",
                  "protocol": "http",
                  "host": [
                    "localhost"
                  ],
                  "port": "5030",
                  "path": [
                    "api",
                    "students"
                  ]
                }
              },
              "response": []
            },
            {
              "name": "Get All Students",
              "request": {
                "method": "GET",
                "header": [],
                "url": {
                  "raw": "http://localhost:5030/api/students",
                  "protocol": "http",
                  "host": [
                    "localhost"
                  ],
                  "port": "5030",
                  "path": [
                    "api",
                    "students"
                  ]
                }
              },
              "response": []
            },
            {
              "name": "Get Student By ID",
              "request": {
                "method": "GET",
                "header": [],
                "url": {
                  "raw": "http://localhost:5030/api/students/STUDENT_ID_HERE",
                  "protocol": "http",
                  "host": [
                    "localhost"
                  ],
                  "port": "5030",
                  "path": [
                    "api",
                    "students",
                    "STUDENT_ID_HERE"
                  ]
                }
              },
              "response": []
            },
            {
              "name": "Get Student By Admission No",
              "request": {
                "method": "GET",
                "header": [],
                "url": {
                  "raw": "http://localhost:5030/api/students/admission/ADM-2026-001",
                  "protocol": "http",
                  "host": [
                    "localhost"
                  ],
                  "port": "5030",
                  "path": [
                    "api",
                    "students",
                    "admission",
                    "ADM-2026-001"
                  ]
                }
              },
              "response": []
            },
            {
              "name": "Get Students By School",
              "request": {
                "method": "GET",
                "header": [],
                "url": {
                  "raw": "http://localhost:5030/api/students/school/6a474d2517e9c40cf971ccc8",
                  "protocol": "http",
                  "host": [
                    "localhost"
                  ],
                  "port": "5030",
                  "path": [
                    "api",
                    "students",
                    "school",
                    "6a474d2517e9c40cf971ccc8"
                  ]
                }
              },
              "response": []
            },
            {
              "name": "Get Students By Class",
              "request": {
                "method": "GET",
                "header": [],
                "url": {
                  "raw": "http://localhost:5030/api/students/class/class-8c",
                  "protocol": "http",
                  "host": [
                    "localhost"
                  ],
                  "port": "5030",
                  "path": [
                    "api",
                    "students",
                    "class",
                    "class-8c"
                  ]
                }
              },
              "response": []
            },
            {
              "name": "Get Students By Parent",
              "request": {
                "method": "GET",
                "header": [],
                "url": {
                  "raw": "http://localhost:5030/api/students/parent/PARENT_ID_HERE",
                  "protocol": "http",
                  "host": [
                    "localhost"
                  ],
                  "port": "5030",
                  "path": [
                    "api",
                    "students",
                    "parent",
                    "PARENT_ID_HERE"
                  ]
                }
              },
              "response": []
            },
            {
              "name": "Get Students By Hostel Room",
              "request": {
                "method": "GET",
                "header": [],
                "url": {
                  "raw": "http://localhost:5030/api/students/hostel/hostel-room-101",
                  "protocol": "http",
                  "host": [
                    "localhost"
                  ],
                  "port": "5030",
                  "path": [
                    "api",
                    "students",
                    "hostel",
                    "hostel-room-101"
                  ]
                }
              },
              "response": []
            },
            {
              "name": "Update Student",
              "request": {
                "method": "PATCH",
                "header": [
                  {
                    "key": "Content-Type",
                    "value": "application/json"
                  }
                ],
                "body": {
                  "mode": "raw",
                  "raw": "{\n  \"firstName\": \"Johnny\",\n  \"status\": \"ACTIVE\"\n}"
                },
                "url": {
                  "raw": "http://localhost:5030/api/students/STUDENT_ID_HERE",
                  "protocol": "http",
                  "host": [
                    "localhost"
                  ],
                  "port": "5030",
                  "path": [
                    "api",
                    "students",
                    "STUDENT_ID_HERE"
                  ]
                }
              },
              "response": []
            },
            {
              "name": "Delete Student",
              "request": {
                "method": "DELETE",
                "header": [],
                "url": {
                  "raw": "http://localhost:5030/api/students/STUDENT_ID_HERE",
                  "protocol": "http",
                  "host": [
                    "localhost"
                  ],
                  "port": "5030",
                  "path": [
                    "api",
                    "students",
                    "STUDENT_ID_HERE"
                  ]
                }
              },
              "response": []
            }
          ]
        },
        {
          "name": "Parents",
          "item": [
            {
              "name": "Create Parent",
              "request": {
                "method": "POST",
                "header": [
                  {
                    "key": "Content-Type",
                    "value": "application/json"
                  }
                ],
                "body": {
                  "mode": "raw",
                  "raw": "{\n  \"schoolId\": \"6a474d2517e9c40cf971ccc1\",\n  \"fatherName\": \"Robert Doe\",\n  \"motherName\": \"Alice Doe\",\n  \"phone\": \"1234567890\",\n  \"alternatePhone\": \"0987654321\",\n  \"email\": \"robert.doe@example.com\",\n  \"address\": \"123 Whispering Pines Road, Cityville\"\n}"
                },
                "url": {
                  "raw": "http://localhost:5030/api/parents",
                  "protocol": "http",
                  "host": [
                    "localhost"
                  ],
                  "port": "5030",
                  "path": [
                    "api",
                    "parents"
                  ]
                }
              },
              "response": []
            },
            {
              "name": "Get All Parents",
              "request": {
                "method": "GET",
                "header": [],
                "url": {
                  "raw": "http://localhost:5030/api/parents",
                  "protocol": "http",
                  "host": [
                    "localhost"
                  ],
                  "port": "5030",
                  "path": [
                    "api",
                    "parents"
                  ]
                }
              },
              "response": []
            },
            {
              "name": "Get Parent By ID",
              "request": {
                "method": "GET",
                "header": [],
                "url": {
                  "raw": "http://localhost:5030/api/parents/PARENT_ID_HERE",
                  "protocol": "http",
                  "host": [
                    "localhost"
                  ],
                  "port": "5030",
                  "path": [
                    "api",
                    "parents",
                    "PARENT_ID_HERE"
                  ]
                }
              },
              "response": []
            },
            {
              "name": "Get Parent By Email",
              "request": {
                "method": "GET",
                "header": [],
                "url": {
                  "raw": "http://localhost:5030/api/parents/email/robert.doe@example.com",
                  "protocol": "http",
                  "host": [
                    "localhost"
                  ],
                  "port": "5030",
                  "path": [
                    "api",
                    "parents",
                    "email",
                    "robert.doe@example.com"
                  ]
                }
              },
              "response": []
            },
            {
              "name": "Get Parents By School",
              "request": {
                "method": "GET",
                "header": [],
                "url": {
                  "raw": "http://localhost:5030/api/parents/school/6a474d2517e9c40cf971ccc8",
                  "protocol": "http",
                  "host": [
                    "localhost"
                  ],
                  "port": "5030",
                  "path": [
                    "api",
                    "parents",
                    "school",
                    "6a474d2517e9c40cf971ccc8"
                  ]
                }
              },
              "response": []
            },
            {
              "name": "Update Parent",
              "request": {
                "method": "PATCH",
                "header": [
                  {
                    "key": "Content-Type",
                    "value": "application/json"
                  }
                ],
                "body": {
                  "mode": "raw",
                  "raw": "{\n  \"fatherName\": \"Robert Doe Sr.\"\n}"
                },
                "url": {
                  "raw": "http://localhost:5030/api/parents/PARENT_ID_HERE",
                  "protocol": "http",
                  "host": [
                    "localhost"
                  ],
                  "port": "5030",
                  "path": [
                    "api",
                    "parents",
                    "PARENT_ID_HERE"
                  ]
                }
              },
              "response": []
            },
            {
              "name": "Delete Parent",
              "request": {
                "method": "DELETE",
                "header": [],
                "url": {
                  "raw": "http://localhost:5030/api/parents/PARENT_ID_HERE",
                  "protocol": "http",
                  "host": [
                    "localhost"
                  ],
                  "port": "5030",
                  "path": [
                    "api",
                    "parents",
                    "PARENT_ID_HERE"
                  ]
                }
              },
              "response": []
            }
          ]
        },
        {
          "name": "Academic Records",
          "item": [
            {
              "name": "Assign Academic Record",
              "request": {
                "method": "POST",
                "header": [
                  {
                    "key": "Content-Type",
                    "value": "application/json"
                  }
                ],
                "body": {
                  "mode": "raw",
                  "raw": "{\n  \"academicYearId\": \"2026-2027\",\n  \"studentId\": \"STD-003-NEW\",\n  \"rollNo\": \"9C-03\",\n  \"classId\": \"class-9c\",\n  \"sectionId\": \"section-c\",\n  \"hostelRoomId\": \"hostel-room-203\",\n  \"status\": \"ACTIVE\"\n}"
                },
                "url": {
                  "raw": "http://localhost:5030/api/students/STUDENT_ID_HERE/academic-records",
                  "protocol": "http",
                  "host": [
                    "localhost"
                  ],
                  "port": "5030",
                  "path": [
                    "api",
                    "students",
                    "STUDENT_ID_HERE",
                    "academic-records"
                  ]
                }
              },
              "response": []
            },
            {
              "name": "Get Student Academic History",
              "request": {
                "method": "GET",
                "header": [],
                "url": {
                  "raw": "http://localhost:5030/api/students/STUDENT_ID_HERE/academic-history",
                  "protocol": "http",
                  "host": [
                    "localhost"
                  ],
                  "port": "5030",
                  "path": [
                    "api",
                    "students",
                    "STUDENT_ID_HERE",
                    "academic-history"
                  ]
                }
              },
              "response": []
            },
            {
              "name": "Promote Student",
              "request": {
                "method": "POST",
                "header": [
                  {
                    "key": "Content-Type",
                    "value": "application/json"
                  }
                ],
                "body": {
                  "mode": "raw",
                  "raw": "{\n  \"academicYearId\": \"2027-2028\",\n  \"studentId\": \"STD-003-PROMOTE\",\n  \"rollNo\": \"10C-03\",\n  \"classId\": \"class-10c\",\n  \"sectionId\": \"section-c\",\n  \"hostelRoomId\": \"hostel-room-303\",\n  \"status\": \"ACTIVE\"\n}"
                },
                "url": {
                  "raw": "http://localhost:5030/api/students/STUDENT_ID_HERE/promote",
                  "protocol": "http",
                  "host": [
                    "localhost"
                  ],
                  "port": "5030",
                  "path": [
                    "api",
                    "students",
                    "STUDENT_ID_HERE",
                    "promote"
                  ]
                }
              },
              "response": []
            }
          ]
        }
      ]
    }
  ]
}